README.md
setup.py
symbiosis_pulumi/__init__.py
symbiosis_pulumi/_inputs.py
symbiosis_pulumi/_utilities.py
symbiosis_pulumi/cluster.py
symbiosis_pulumi/cluster_service_account.py
symbiosis_pulumi/node_pool.py
symbiosis_pulumi/outputs.py
symbiosis_pulumi/provider.py
symbiosis_pulumi/pulumi-plugin.json
symbiosis_pulumi/py.typed
symbiosis_pulumi/team_member.py
symbiosis_pulumi.egg-info/PKG-INFO
symbiosis_pulumi.egg-info/SOURCES.txt
symbiosis_pulumi.egg-info/dependency_links.txt
symbiosis_pulumi.egg-info/not-zip-safe
symbiosis_pulumi.egg-info/requires.txt
symbiosis_pulumi.egg-info/top_level.txt
symbiosis_pulumi/config/__init__.py
symbiosis_pulumi/config/vars.py