Metadata-Version: 2.1
Name: symbiosis-pulumi
Version: 1.0.4
Summary: A Pulumi package for creating and managing symbiosis cloud resources.
Home-page: https://www.pulumi.com
License: Apache-2.0
Project-URL: Repository, https://github.com/symbiosis-cloud/pulumi-symbiosis
Keywords: pulumi symbiosis category/cloud
Platform: UNKNOWN
